[
    {
        "id": "9bb1c5e1-dbb3-4407-be0e-3cc0dc45bf1a",
        "name": "Marathon Match 136",
        "submissionStartDate": "2022-04-21T14:42:10Z",
        "submissionEndDate": "2022-05-25T17:14:11Z",
        "tcoRelevant": true,
        "leaderboard": [
            {
                "name": "ebicochineal",
                "score": 82.590
            },
            {
                "name": "macs",
                "score": -1
            },
            {
                "name": "FAndES",
                "score": 66.50233738535651
            },
            {
                "name": "pedrosorio",
                "score": 30.657233502857398
            },
            {
                "name": "Aruru",
                "score": 54.61344285280208
            },
            {
                "name": "Psyho",
                "score": 97.34636907570714
            },
            {
                "name": "highjump",
                "score": 62.28704876363444
            },
            {
                "name": "terry_u16",
                "score": 88.60328178069945
            },
            {
                "name": "sca1l",
                "score": 42.10136881189788
            },
            {
                "name": "mengue",
                "score": 26.90826038917884
            },
            {
                "name": "wanui",
                "score": 85.02309161505693
            },
            {
                "name": "phocom",
                "score": 23.742812002919948
            },
            {
                "name": "NavierBoltzmann",
                "score": 57.69745843453038
            },
            {
                "name": "CatalinT",
                "score": 44.86079543247203
            },
            {
                "name": "vdave",
                "score": 58.386834766798856
            },
            {
                "name": "therealbeef",
                "score": 32.358169750280744
            },
            {
                "name": "nejineji",
                "score": 90.18003424275226
            },
            {
                "name": "eulerscheZahl",
                "score": 87.81954757447174
            },
            {
                "name": "a9ua1i0n",
                "score": 31.24287251914049
            },
            {
                "name": "EvbCFfp1XB",
                "score": 84.10465965927686
            },
            {
                "name": "lordoskar",
                "score": 24.14256643287442
            },
            {
                "name": "JacoCronje",
                "score": 81.87343174106127
            },
            {
                "name": "tashikani",
                "score": 75.042445143288
            },
            {
                "name": "tanzaku",
                "score": 92.59997778199593
            },
            {
                "name": "simanman",
                "score": 89.84874969622008
            },
            {
                "name": "ssaattoo",
                "score": 38.71942790420761
            },
            {
                "name": "nofto",
                "score": 64.9652695979446
            },
            {
                "name": "ATowerOfHanoi",
                "score": 72.29627611480623
            },
            {
                "name": "ozy4dm",
                "score": 69.07729888190059
            },
            {
                "name": "blackmath",
                "score": 94.22074216062799
            },
            {
                "name": "tygrysek",
                "score": 58.25316053719777
            },
            {
                "name": "gardn999",
                "score": 68.44135334029959
            },
            {
                "name": "FranciscoGeiman",
                "score": 41.34857818789584
            },
            {
                "name": "wleite",
                "score": 87.3482727749377
            },
            {
                "name": "Stonefeang",
                "score": 94.02430923317155
            },
            {
                "name": "dwij",
                "score": 21.47515813710686
            },
            {
                "name": "tooooooo0000000",
                "score": 24.905658545281234
            },
            {
                "name": "shamio",
                "score": 80.83218462089356
            },
            {
                "name": "jona2jef",
                "score": -1
            },
            {
                "name": "Daiver19",
                "score": 87.30422194904872
            },
            {
                "name": "mooaki",
                "score": 32.31196537129891
            },
            {
                "name": "SubCero",
                "score": 21.446610258440266
            },
            {
                "name": "JT8218",
                "score": 14.986064006942136
            },
            {
                "name": "AjJi",
                "score": 24.505126489415016
            },
            {
                "name": "daisyo",
                "score": 22.240534576368333
            },
            {
                "name": "hiro116s",
                "score": 65.36767841738798
            },
            {
                "name": "colun",
                "score": 87.9318641658723
            },
            {
                "name": "rballman",
                "score": 21.029113894062704
            },
            {
                "name": "PlayLikeNeverB4",
                "score": 71.80291118403096
            },
            {
                "name": "RafbillFr",
                "score": 89.95524072966396
            },
            {
                "name": "my316g",
                "score": 23.697250942708113
            },
            {
                "name": "brthyyjp",
                "score": 16.830285610030796
            },
            {
                "name": "hamuhei4869",
                "score": 39.95203609851636
            },
            {
                "name": "xIlledanx",
                "score": 54.39515510682302
            },
            {
                "name": "Mayimg",
                "score": 45.48312989778233
            },
            {
                "name": "vlad_D",
                "score": 63.39545318008075
            },
            {
                "name": "hydru",
                "score": -1
            },
            {
                "name": "isseimori127",
                "score": 21.65844720967802
            },
            {
                "name": "onjanirina",
                "score": 17.549905139235044
            }
        ]
    },
    {
        "id": "ef5d19d2-de9b-4e37-b428-e7e103458425",
        "name": "Marathon Match 135",
        "submissionStartDate": "2022-04-06T17:21:10Z",
        "submissionEndDate": "2022-04-26T21:09:14Z",
        "tcoRelevant": true,
        "leaderboard": [
            {
                "name": "blackmath",
                "score": 93.4508139182005
            },
            {
                "name": "FranciscoGeiman",
                "score": 27.284641715690277
            },
            {
                "name": "CatalinT",
                "score": 84.84523302588494
            },
            {
                "name": "titia",
                "score": 57.64113412230932
            },
            {
                "name": "akTARDIGRADE13",
                "score": 37.67857299694645
            },
            {
                "name": "Inaniwa",
                "score": 60.4889507845082
            },
            {
                "name": "colun",
                "score": 91.76615337164992
            },
            {
                "name": "phocom",
                "score": 39.75144569849407
            },
            {
                "name": "nofto",
                "score": 71.32823219628116
            },
            {
                "name": "JacoCronje",
                "score": 94.31015094193468
            },
            {
                "name": "sca1l",
                "score": 40.9394794441529
            },
            {
                "name": "ozy4dm",
                "score": 52.79122752406561
            },
            {
                "name": "bphillips123",
                "score": -1
            },
            {
                "name": "kaede2020",
                "score": 12.817460967399827
            },
            {
                "name": "EvbCFfp1XB",
                "score": 32.89199117265438
            },
            {
                "name": "my316g",
                "score": 30.51574463804266
            },
            {
                "name": "iehn",
                "score": 82.87863762008827
            },
            {
                "name": "tanzaku",
                "score": 91.8162072931183
            },
            {
                "name": "eulerscheZahl",
                "score": 84.880050656482
            },
            {
                "name": "ebicochineal",
                "score": 86.99489620117883
            },
            {
                "name": "xIlledanx",
                "score": 29.270723679001467
            },
            {
                "name": "mooaki",
                "score": 69.57707551834149
            },
            {
                "name": "hari64",
                "score": 68.59276961002288
            },
            {
                "name": "yoika",
                "score": 20.19710178742642
            },
            {
                "name": "ATowerOfHanoi",
                "score": 59.35043684170642
            },
            {
                "name": "highjump",
                "score": 67.25382650789548
            },
            {
                "name": "kahuka",
                "score": 48.72399438295946
            },
            {
                "name": "toku_",
                "score": 56.05394349462791
            },
            {
                "name": "vlad_D",
                "score": 35.39836317239855
            },
            {
                "name": "yowa",
                "score": 90.54827116496698
            },
            {
                "name": "nejineji",
                "score": 66.1432512871213
            },
            {
                "name": "Daiver19",
                "score": 90.32373849742584
            },
            {
                "name": "ssaattoo",
                "score": 50.47789703281177
            },
            {
                "name": "Stonefeang",
                "score": 96.7397044543164
            },
            {
                "name": "NavierBoltzmann",
                "score": 4.832152855098471
            },
            {
                "name": "brthyyjp",
                "score": 4.832152855098471
            },
            {
                "name": "PlayLikeNeverB4",
                "score": 29.157816018908786
            },
            {
                "name": "abhi964",
                "score": 5.0214751695037165
            },
            {
                "name": "hamuhei4869",
                "score": -1
            },
            {
                "name": "shojin_pro",
                "score": 14.73448617798092
            },
            {
                "name": "RafbillFr",
                "score": 1
            },
            {
                "name": "mmm-m",
                "score": 32.89200052909178
            },
            {
                "name": "soraie",
                "score": 4.832152855098471
            },
            {
                "name": "code2016",
                "score": 4.832152855098471
            }
        ]
    },
    {
        "id": "bb34cc95-c06c-4ef7-8655-db0095e45ca3",
        "name": "Cognitive State Determination - Fault Tolerance Marathon Match",
        "submissionStartDate": "2022-04-01T13:13:56Z",
        "submissionEndDate": "2022-04-18T13:28:28Z",
        "tcoRelevant": true,
        "leaderboard": [
            {
                "name": "fly_fly",
                "score": 79.74535
            },
            {
                "name": "SayantanDey",
                "score": 23.23503
            },
            {
                "name": "rtty",
                "score": 37.9254
            },
            {
                "name": "umeco",
                "score": -1
            },
            {
                "name": "waynn",
                "score": 31.51922
            },
            {
                "name": "Dylan_Liu",
                "score": 71.29225
            },
            {
                "name": "viyaviya",
                "score": 67.79346
            },
            {
                "name": "tEarth",
                "score": 68.98005
            },
            {
                "name": "Z.paint",
                "score": -1
            },
            {
                "name": "talesdias47902",
                "score": -1
            },
            {
                "name": "pjmathematician",
                "score": -1
            }
        ]
    },
    {
        "id": "6703e307-7c93-4240-988f-38c1d93cf25c",
        "name": "Topcoder Learning Path Ideation and Feedback Series - Data Science",
        "submissionStartDate": "2022-03-24T09:37:09Z",
        "submissionEndDate": "2022-03-29T09:55:26Z",
        "tcoRelevant": false,
        "leaderboard": []
    },
    {
        "id": "364e2cc2-0070-4d93-b499-cc1b2073bfe3",
        "name": "Pickup and Delivery Problem with Transfer and Time Window Mini Marathon Challenge Part4",
        "submissionStartDate": "2022-03-18T14:25:59Z",
        "submissionEndDate": "2022-04-11T04:29:06Z",
        "tcoRelevant": true,
        "leaderboard": [
            {
                "name": "SayantanDey",
                "score": -1
            },
            {
                "name": "wleite",
                "score": 46.296389
            },
            {
                "name": "PlayLikeNeverB4",
                "score": 5.20247
            },
            {
                "name": "mengue",
                "score": 0
            },
            {
                "name": "viyaviya",
                "score": 0
            },
            {
                "name": "ihdijk",
                "score": 0
            },
            {
                "name": "pfilippi",
                "score": 0
            },
            {
                "name": "sndyuk",
                "score": 0
            }
        ]
    },
    {
        "id": "e067d47e-7d88-459a-9fc0-af6a44447f2a",
        "name": "TCO Structure Idea Generation Challenge",
        "submissionStartDate": "2022-03-16T18:26:29Z",
        "submissionEndDate": "2022-04-01T18:32:27Z",
        "tcoRelevant": false,
        "leaderboard": []
    },
    {
        "id": "5ac77343-7f2f-4635-8aff-bbf49c700fda",
        "name": "Marathon Match 134",
        "submissionStartDate": "2022-03-10T13:05:46Z",
        "submissionEndDate": "2022-03-23T20:07:23Z",
        "tcoRelevant": true,
        "leaderboard": [
            {
                "name": "sogrub",
                "score": 0.16905575669555808
            },
            {
                "name": "ty70",
                "score": 42.42093852337037
            },
            {
                "name": "Ra16bit",
                "score": -1
            },
            {
                "name": "umeco",
                "score": 60.707134963984394
            },
            {
                "name": "nofto",
                "score": 92.83107004721104
            },
            {
                "name": "ap31",
                "score": 85.61048376699132
            },
            {
                "name": "ozy4dm",
                "score": 89.9295405194564
            },
            {
                "name": "highjump",
                "score": 94.18803476206558
            },
            {
                "name": "kaede2020",
                "score": 84.5125462944872
            },
            {
                "name": "craig.miller3",
                "score": 80.1736207987091
            },
            {
                "name": "phocom",
                "score": 87.29239807837853
            },
            {
                "name": "KawattaTaido",
                "score": 93.14220988712998
            },
            {
                "name": "eulerscheZahl",
                "score": 96.99225189311278
            },
            {
                "name": "ekiden",
                "score": 85.42951159481245
            },
            {
                "name": "mooaki",
                "score": 89.29984834205099
            },
            {
                "name": "EvbCFfp1XB",
                "score": 91.42219903469216
            },
            {
                "name": "yowa",
                "score": 95.76585362648123
            },
            {
                "name": "ATowerOfHanoi",
                "score": 88.2609779443258
            },
            {
                "name": "simanman",
                "score": 95.6721185658264
            },
            {
                "name": "hari64",
                "score": 89.91286505099878
            },
            {
                "name": "nejineji",
                "score": 94.1944373314487
            },
            {
                "name": "platinum_prog",
                "score": 86.50978697321698
            },
            {
                "name": "iehn",
                "score": 96.55757389453971
            },
            {
                "name": "mmm-m",
                "score": 88.94269119992764
            },
            {
                "name": "hamuhei4869",
                "score": 70.20800725077673
            },
            {
                "name": "shamio",
                "score": 90.190988543009
            },
            {
                "name": "Daiver19",
                "score": 94.77997683773671
            },
            {
                "name": "ebicochineal",
                "score": 93.05806297196143
            },
            {
                "name": "xIlledanx",
                "score": 88.48908567945246
            },
            {
                "name": "FranciscoGeiman",
                "score": 81.0774734273845
            },
            {
                "name": "ptoolis",
                "score": 48.78413071943014
            },
            {
                "name": "tygrysek",
                "score": 89.08939717167479
            },
            {
                "name": "therealbeef",
                "score": 61.210574731585005
            },
            {
                "name": "TopG",
                "score": -1
            },
            {
                "name": "daisyo",
                "score": 86.11843649861298
            },
            {
                "name": "ssaattoo",
                "score": 82.09555165291056
            },
            {
                "name": "bohuss",
                "score": 85.00999657245357
            },
            {
                "name": "coderbd",
                "score": 61.574150210714535
            },
            {
                "name": "m8rex",
                "score": 83.84286311952435
            },
            {
                "name": "M315",
                "score": 60.6413583507794
            },
            {
                "name": "PlayLikeNeverB4",
                "score": 83.15567692055262
            },
            {
                "name": "nika",
                "score": 89.80290364592923
            },
            {
                "name": "rmizuta",
                "score": 75.9265972398361
            },
            {
                "name": "brthyyjp",
                "score": 62.025026333753544
            },
            {
                "name": "Mayimg",
                "score": 91.10823371532194
            },
            {
                "name": "vlad_D",
                "score": 84.04215801817092
            },
            {
                "name": "tuff",
                "score": 79.46330914327207
            }
        ]
    },
    {
        "id": "d7731cb4-99ec-42e3-bc2a-7d476109c7eb",
        "name": "Language Identification Improvement & API Python Challenge",
        "submissionStartDate": "2022-02-23T22:40:55Z",
        "submissionEndDate": "2022-03-02T04:52:45Z",
        "tcoRelevant": false,
        "leaderboard": []
    },
    {
        "id": "81f14f36-e87a-445d-96d0-9f7d4e263be3",
        "name": "Design a crypto coin",
        "submissionStartDate": "2022-02-03T16:32:18Z",
        "submissionEndDate": "2022-02-11T04:59:51Z",
        "tcoRelevant": false,
        "leaderboard": []
    },
    {
        "id": "075971a4-e4e4-4dec-aea0-ade30812d470",
        "name": "Word-level Language Identification Python Challenge",
        "submissionStartDate": "2022-01-19T15:05:47Z",
        "submissionEndDate": "2022-01-24T15:09:34Z",
        "tcoRelevant": false,
        "leaderboard": []
    },
    {
        "id": "5fb2b54f-055e-4059-8687-ebaa8dbd8a18",
        "name": "Marathon Match 133",
        "submissionStartDate": "2022-01-18T17:34:16Z",
        "submissionEndDate": "2022-02-16T18:09:04Z",
        "tcoRelevant": true,
        "leaderboard": [
            {
                "name": "xsabi",
                "score": 1.3543346939148893
            },
            {
                "name": "ap31",
                "score": -1
            },
            {
                "name": "garyah",
                "score": 1.1572796363400857
            },
            {
                "name": "nika",
                "score": 91.81925418514649
            },
            {
                "name": "phocom",
                "score": 12.280658326797306
            },
            {
                "name": "nofto",
                "score": 52.596811414624455
            },
            {
                "name": "tashikani",
                "score": 35.99735590826071
            },
            {
                "name": "eulerscheZahl",
                "score": 62.09913261030667
            },
            {
                "name": "tygrysek",
                "score": 25.303649921695193
            },
            {
                "name": "yowa",
                "score": 74.39136974508577
            },
            {
                "name": "perseus79",
                "score": 6.92031444910072
            },
            {
                "name": "abhinav4279",
                "score": 1.2266537152702164
            },
            {
                "name": "Daiver19",
                "score": 70.16875972528089
            },
            {
                "name": "ATowerOfHanoi",
                "score": 5.232674978105472
            },
            {
                "name": "EvbCFfp1XB",
                "score": 8.615717785045758
            },
            {
                "name": "M.Saito",
                "score": 42.14949022371509
            },
            {
                "name": "Acarreo",
                "score": 17.177500795147665
            },
            {
                "name": "qma",
                "score": 47.91440075797121
            },
            {
                "name": "devang1998",
                "score": -1
            },
            {
                "name": "Stefan70",
                "score": 56.63863117150209
            },
            {
                "name": "platinum_prog",
                "score": 2.5051654601573805
            },
            {
                "name": "wleite",
                "score": 62.2938169412693
            },
            {
                "name": "robostac",
                "score": 17.987918507700815
            },
            {
                "name": "mcw1142",
                "score": 2.78412979274405
            },
            {
                "name": "vlad_D",
                "score": 44.06194402045148
            },
            {
                "name": "abhiiitcse",
                "score": 1.1120153110199567
            },
            {
                "name": "tuff",
                "score": 17.59674461343865
            },
            {
                "name": "simanman",
                "score": 52.942690265847084
            },
            {
                "name": "toku_",
                "score": 49.19377493718824
            },
            {
                "name": "beginnner101",
                "score": 0.02594506653040386
            },
            {
                "name": "mooaki",
                "score": 2.0006883006991067
            },
            {
                "name": "highjump",
                "score": 12.61385527372145
            },
            {
                "name": "iehn",
                "score": 19.969665626519717
            },
            {
                "name": "xIlledanx",
                "score": 1.0058095761335901
            },
            {
                "name": "mengue",
                "score": 0.13234262052290657
            }
        ]
    },
    {
        "id": "fcad16e0-9ca6-4510-8bd9-af3ed026b140",
        "name": "NASA Comet Detection Marathon Match",
        "submissionStartDate": "2022-01-17T14:39:52Z",
        "submissionEndDate": "2022-02-14T14:42:35Z",
        "tcoRelevant": true,
        "leaderboard": [
            {
                "name": "fardeen_2006",
                "score": -1
            },
            {
                "name": "cannab",
                "score": 46.00567
            },
            {
                "name": "ap31",
                "score": 38.2639
            },
            {
                "name": "a.lowe",
                "score": 0.8307770229295681
            },
            {
                "name": "JinhyeonKim",
                "score": 6.99112
            },
            {
                "name": "pberrett",
                "score": 1.8455822172011
            },
            {
                "name": "cjp68",
                "score": 0.138803580612803
            },
            {
                "name": "ceres1",
                "score": 66.21271
            },
            {
                "name": "rkinnett",
                "score": 0.747942832261158
            },
            {
                "name": "ZFTurbo",
                "score": 39.15259
            },
            {
                "name": "kruntuid",
                "score": 37.99806
            },
            {
                "name": "integratiab",
                "score": 0.626500736787992
            },
            {
                "name": "gardn999",
                "score": 62.20877
            },
            {
                "name": "selim_sef",
                "score": 60.41316
            },
            {
                "name": "dimkadimon",
                "score": 14.72728
            },
            {
                "name": "sorokinv",
                "score": 0.00209087777172735
            },
            {
                "name": "ABHIJAT_SARARI",
                "score": -1
            },
            {
                "name": "stewi2",
                "score": 0.687474897779299
            },
            {
                "name": "MarathonTester2",
                "score": -1
            },
            {
                "name": "viyaviya",
                "score": -1
            },
            {
                "name": "Rokit12",
                "score": -1
            },
            {
                "name": "abdullah0096",
                "score": 0.6169528425054001
            },
            {
                "name": "cs_lewy",
                "score": 0.530502276454591
            },
            {
                "name": "ritesh_cs",
                "score": -1
            },
            {
                "name": "victorkras2008",
                "score": 0.582312775409625
            },
            {
                "name": "buryakigr",
                "score": 0.583016590059071
            },
            {
                "name": "srinath_ssn",
                "score": -1
            }
        ]
    },
    {
        "id": "3a6b8bf2-1e02-4acb-a50a-09a13ed9ba34",
        "name": "Marathon Match 132",
        "submissionStartDate": "2022-01-04T18:09:12Z",
        "submissionEndDate": "2022-01-19T18:15:17Z",
        "tcoRelevant": true,
        "leaderboard": [
            {
                "name": "phocom",
                "score": 35.34160888371067
            },
            {
                "name": "nika",
                "score": 82.06145727380265
            },
            {
                "name": "titia",
                "score": 22.516692315975803
            },
            {
                "name": "CatalinT",
                "score": 29.189762520083335
            },
            {
                "name": "Inaniwa",
                "score": 36.538267796755626
            },
            {
                "name": "toku_",
                "score": 33.97263639416187
            },
            {
                "name": "Acarreo",
                "score": 35.71700204139846
            },
            {
                "name": "eulerscheZahl",
                "score": 37.75826139623914
            },
            {
                "name": "nofto",
                "score": 35.55923718228373
            },
            {
                "name": "sogrub",
                "score": 1.7512360943087883
            },
            {
                "name": "vlad_D",
                "score": 46.45299807290862
            },
            {
                "name": "KawattaTaido",
                "score": 32.657618200162574
            },
            {
                "name": "mugurelionut",
                "score": 56.36594701948272
            },
            {
                "name": "ebicochineal",
                "score": 38.455810724700946
            },
            {
                "name": "iehn",
                "score": 38.977193251020964
            },
            {
                "name": "simanman",
                "score": 65.47688811495401
            },
            {
                "name": "sullyper",
                "score": 83.72971196039033
            },
            {
                "name": "kaede2020",
                "score": 3.2609508283543978
            },
            {
                "name": "tashikani",
                "score": 34.00575936664314
            },
            {
                "name": "bowwowforeach",
                "score": 48.38370828168059
            },
            {
                "name": "rmizuta",
                "score": 18.140456594092903
            },
            {
                "name": "ATowerOfHanoi",
                "score": 27.66968803974102
            },
            {
                "name": "platinum_prog",
                "score": 21.486609903860856
            },
            {
                "name": "skrzypl1",
                "score": 28.15072581856321
            },
            {
                "name": "vdave",
                "score": 38.81484081266997
            },
            {
                "name": "Aruru",
                "score": 39.07957752806953
            },
            {
                "name": "Daiver19",
                "score": 55.419038079128484
            },
            {
                "name": "gardn999",
                "score": 35.34278842311647
            },
            {
                "name": "pranavi96",
                "score": 0.5676304572361707
            },
            {
                "name": "yowa",
                "score": 33.95550407763695
            },
            {
                "name": "xIlledanx",
                "score": 26.512010847078134
            },
            {
                "name": "michalkowalski",
                "score": 12.476517747200672
            },
            {
                "name": "tygrysek",
                "score": 27.086351616072594
            },
            {
                "name": "wleite",
                "score": 56.865928135301694
            },
            {
                "name": "jediller",
                "score": 7.42579250676098
            },
            {
                "name": "mooaki",
                "score": 20.881010733433715
            },
            {
                "name": "gultai4uk_r",
                "score": 5.582602457385038
            },
            {
                "name": "EvbCFfp1XB",
                "score": 33.26192839418889
            },
            {
                "name": "tomerun",
                "score": 23.473806045672298
            },
            {
                "name": "highjump",
                "score": 35.94615251759022
            },
            {
                "name": "shamio",
                "score": 28.48671627191566
            },
            {
                "name": "hari64",
                "score": 5.228429979678142
            },
            {
                "name": "my316g",
                "score": 32.697136289454455
            }
        ]
    },
    {
        "id": "74c9ea5d-62f5-4168-8f2e-f05d2694988a",
        "name": "Cognitive State Determination Marathon Match",
        "submissionStartDate": "2021-12-21T14:38:34Z",
        "submissionEndDate": "2022-01-24T14:43:27Z",
        "tcoRelevant": true,
        "leaderboard": [
            {
                "name": "SayantanDey",
                "score": 97.66143
            },
            {
                "name": "Prepod",
                "score": 93.76569
            },
            {
                "name": "nickil21",
                "score": 97.27574
            },
            {
                "name": "marcocastangia",
                "score": 97.93984
            },
            {
                "name": "ap31",
                "score": 85.03405
            },
            {
                "name": "vdave",
                "score": 90.94221
            },
            {
                "name": "rayvanve",
                "score": 98.1132
            },
            {
                "name": "mugurelionut",
                "score": 98.4137
            },
            {
                "name": "Dylan_Liu",
                "score": 99.03744
            },
            {
                "name": "Ilya.Chernov",
                "score": 94.95587
            },
            {
                "name": "AliGebily",
                "score": 94.67644
            },
            {
                "name": "myterisa",
                "score": 92.97681
            },
            {
                "name": "tEarth",
                "score": 98.88857
            },
            {
                "name": "LastEmperor",
                "score": 97.34668
            },
            {
                "name": "cs_lewy",
                "score": 92.2584
            }
        ]
    },
    {
        "id": "efd27158-8826-4c37-a1a1-0d62718442a7",
        "name": "Capacitated Vehicle Routing Problem with Time Window Mini Marathon Challenge Part3",
        "submissionStartDate": "2021-12-17T14:14:17Z",
        "submissionEndDate": "2021-12-27T09:18:32Z",
        "tcoRelevant": true,
        "leaderboard": [
            {
                "name": "vlad_D",
                "score": 43.305212
            },
            {
                "name": "vdave",
                "score": 65.234955
            },
            {
                "name": "sullyper",
                "score": 45.086912
            },
            {
                "name": "ap31",
                "score": 65.806518
            },
            {
                "name": "wleite",
                "score": 75.781831
            },
            {
                "name": "tongkunvwang",
                "score": 13.940957
            },
            {
                "name": "mugurelionut",
                "score": 48.402733
            },
            {
                "name": "SayantanDey",
                "score": 19.724841
            }
        ]
    },
    {
        "id": "0e0f7d6d-1308-498c-b2f1-607d32d1ed61",
        "name": "EDG Databricks Cluster Data Load Prediction Model Challenge",
        "submissionStartDate": "2021-12-06T11:16:21Z",
        "submissionEndDate": "2021-12-17T11:19:48Z",
        "tcoRelevant": false,
        "leaderboard": []
    },
    {
        "id": "d23f152d-160d-459d-a9c7-b95e02161675",
        "name": "Soro Journal Search Engine PoC Codebase Development Challenge",
        "submissionStartDate": "2021-11-20T01:47:55Z",
        "submissionEndDate": "2021-11-30T01:48:10Z",
        "tcoRelevant": false,
        "leaderboard": []
    },
    {
        "id": "00b375b6-1f64-4702-baeb-28a7b00b64d1",
        "name": "Marathon Match 131",
        "submissionStartDate": "2021-11-18T21:30:23Z",
        "submissionEndDate": "2021-12-22T18:33:17Z",
        "tcoRelevant": true,
        "leaderboard": [
            {
                "name": "titia",
                "score": 69.01481114510155
            },
            {
                "name": "Inaniwa",
                "score": 79.9154581246658
            },
            {
                "name": "ap31",
                "score": 79.74879093234975
            },
            {
                "name": "nofto",
                "score": 87.09204166694943
            },
            {
                "name": "phocom",
                "score": 73.78055970154713
            },
            {
                "name": "nika",
                "score": 90.29740903438777
            },
            {
                "name": "gardn999",
                "score": 76.80770420014922
            },
            {
                "name": "hamuhei4869",
                "score": 71.56383047963338
            },
            {
                "name": "mugurelionut",
                "score": 81.47901025093638
            },
            {
                "name": "Psyho",
                "score": 88.22140142791746
            },
            {
                "name": "eulerscheZahl",
                "score": 87.50505550121112
            },
            {
                "name": "highjump",
                "score": 83.73702719623385
            },
            {
                "name": "lordoskar",
                "score": 61.41500765501607
            },
            {
                "name": "tygrysek",
                "score": 78.50415118726167
            },
            {
                "name": "tashikani",
                "score": 75.29351928914333
            },
            {
                "name": "simanman",
                "score": 82.32756323807934
            },
            {
                "name": "sullyper",
                "score": 92.03192898789978
            },
            {
                "name": "ATowerOfHanoi",
                "score": 66.10270138274984
            },
            {
                "name": "mooaki",
                "score": 68.48234917339784
            },
            {
                "name": "hari64",
                "score": 69.91518913328186
            },
            {
                "name": "kaede2020",
                "score": 56.80620370293513
            },
            {
                "name": "shamio",
                "score": 78.27881821125271
            },
            {
                "name": "xIlledanx",
                "score": 75.59735979481988
            },
            {
                "name": "Daiver19",
                "score": 83.03845725323839
            },
            {
                "name": "vdave",
                "score": 74.92286891787234
            },
            {
                "name": "Astrobytes",
                "score": 37.77714335199302
            },
            {
                "name": "birdofpreyru",
                "score": 79.96677457988389
            },
            {
                "name": "vlad_D",
                "score": 79.9119891642745
            },
            {
                "name": "sogrub",
                "score": 9.699998886228537
            },
            {
                "name": "sarthakmanna",
                "score": -1
            },
            {
                "name": "my316g",
                "score": 72.52725055716752
            },
            {
                "name": "RafbillFr",
                "score": 85.66598865289755
            },
            {
                "name": "jediller",
                "score": 52.0671482375843
            },
            {
                "name": "toku_",
                "score": 79.4099757400279
            },
            {
                "name": "EvbCFfp1XB",
                "score": 73.03707939407447
            },
            {
                "name": "yowa",
                "score": 77.21847507511255
            },
            {
                "name": "zettix",
                "score": 60.465517404128136
            },
            {
                "name": "mazesoba",
                "score": 50.96198017315386
            },
            {
                "name": "andresduque",
                "score": 65.72598467334652
            },
            {
                "name": "rmizuta",
                "score": 57.035285625821466
            },
            {
                "name": "NavierBoltzmann",
                "score": 12.493476967386046
            },
            {
                "name": "kumarbaibhav",
                "score": 12.493476967386046
            },
            {
                "name": "iehn",
                "score": 73.25502395136296
            },
            {
                "name": "Mayimg",
                "score": 66.0042338479177
            },
            {
                "name": "MarathonTester2",
                "score": 56.422652706871126
            },
            {
                "name": "sebastiens",
                "score": 12.493476967386046
            },
            {
                "name": "mengue",
                "score": 12.493476967386046
            },
            {
                "name": "yuusanlondon",
                "score": 47.223447284651726
            },
            {
                "name": "reg7777",
                "score": 29.512024353270448
            },
            {
                "name": "Stonefeang",
                "score": 77.90308038695946
            },
            {
                "name": "mtsaka",
                "score": 12.493476967386046
            }
        ]
    },
    {
        "id": "eab61248-dcf2-4a3b-aa72-62c703d9a7dd",
        "name": "Marathon Match 130",
        "submissionStartDate": "2021-10-01T05:40:08Z",
        "submissionEndDate": "2021-10-20T16:44:47Z",
        "tcoRelevant": true,
        "leaderboard": [
            {
                "name": "tourist",
                "score": 75.44868178988648
            },
            {
                "name": "phocom",
                "score": 90.40464457298006
            },
            {
                "name": "KKT89",
                "score": 49.99092565130434
            },
            {
                "name": "Inaniwa",
                "score": 54.35916846259742
            },
            {
                "name": "sullyper",
                "score": 93.52596991013867
            },
            {
                "name": "JRandomHacker",
                "score": 35.87693031216347
            },
            {
                "name": "RafbillFr",
                "score": 96.61860505524555
            },
            {
                "name": "vdave",
                "score": 92.79504941326023
            },
            {
                "name": "nailBiter",
                "score": 2.9529947525052065
            },
            {
                "name": "darnley",
                "score": 88.31082929346604
            },
            {
                "name": "mugurelionut",
                "score": 96.11165612209955
            },
            {
                "name": "tomerun",
                "score": 56.94606624453517
            },
            {
                "name": "wleite",
                "score": 96.91568734578794
            },
            {
                "name": "nika",
                "score": 95.92037265946252
            },
            {
                "name": "my316g",
                "score": 92.22517161491267
            },
            {
                "name": "udon1206",
                "score": 56.92683825418907
            },
            {
                "name": "nofto",
                "score": 85.29358549070989
            },
            {
                "name": "perseus79",
                "score": 80.63768014529172
            },
            {
                "name": "kaede2020",
                "score": 3.338888543064962
            },
            {
                "name": "EvbCFfp1XB",
                "score": 50.123300561330076
            },
            {
                "name": "kahuka",
                "score": 49.68821336364437
            },
            {
                "name": "ekiden",
                "score": 51.650854685999875
            },
            {
                "name": "hari64",
                "score": 80.07744958992426
            },
            {
                "name": "bowwowforeach",
                "score": 58.37907414497716
            },
            {
                "name": "shamio",
                "score": 50.274171411264675
            },
            {
                "name": "vpike",
                "score": 84.90617651137156
            },
            {
                "name": "shim0",
                "score": 25.458588247559153
            },
            {
                "name": "ptoolis",
                "score": 43.375637181501304
            },
            {
                "name": "rmizuta",
                "score": 33.39146851543704
            },
            {
                "name": "mooaki",
                "score": 45.7801844566638
            },
            {
                "name": "Daiver19",
                "score": 93.34914139301202
            },
            {
                "name": "mezzou",
                "score": 16.33806247280793
            },
            {
                "name": "gardn999",
                "score": 55.81929286327093
            },
            {
                "name": "ebicochineal",
                "score": 58.42933797771002
            },
            {
                "name": "vlad_D",
                "score": 88.36337267438294
            },
            {
                "name": "Degalat57",
                "score": 86.20053928986167
            },
            {
                "name": "kelagnir",
                "score": 1
            },
            {
                "name": "yowa",
                "score": 90.82647172142038
            },
            {
                "name": "kalesnikauilya",
                "score": 48.63775501864715
            },
            {
                "name": "toku_",
                "score": 92.13991235238379
            },
            {
                "name": "highjump",
                "score": 55.50339170136361
            },
            {
                "name": "okazaki",
                "score": 53.038829359857914
            },
            {
                "name": "eulerscheZahl",
                "score": 47.070619101193365
            },
            {
                "name": "ty70",
                "score": 1
            },
            {
                "name": "goto_isyuku",
                "score": 21.475039710505175
            },
            {
                "name": "torisasami_",
                "score": 42.79283201979293
            },
            {
                "name": "kozima",
                "score": 59.6840459698236
            },
            {
                "name": "terry_u16",
                "score": 52.53331323151135
            },
            {
                "name": "mcw1142",
                "score": 0.03628622522396856
            },
            {
                "name": "4bungi",
                "score": 58.343538785704666
            },
            {
                "name": "tuff",
                "score": 91.13310540909394
            },
            {
                "name": "houxiang",
                "score": 39.69145753804556
            },
            {
                "name": "rballman",
                "score": 41.763621090296205
            },
            {
                "name": "abundrew",
                "score": 35.60116894080673
            },
            {
                "name": "abhiiitcse",
                "score": 46.54052645543339
            },
            {
                "name": "_Romka_",
                "score": 41.272577477235046
            },
            {
                "name": "rosso01",
                "score": 1.8453789173937483
            },
            {
                "name": "mengue",
                "score": 44.70669214611621
            },
            {
                "name": "leopro",
                "score": 6.064558620670735
            },
            {
                "name": "yuusanlondon",
                "score": 46.681988719946744
            },
            {
                "name": "tehnar",
                "score": 48.239503169151874
            },
            {
                "name": "simanman",
                "score": 61.907852248825485
            },
            {
                "name": "kyoran",
                "score": 31.433825606173574
            },
            {
                "name": "iehn",
                "score": 57.9568687873376
            },
            {
                "name": "ATowerOfHanoi",
                "score": 38.4657011761455
            },
            {
                "name": "kronos111",
                "score": 28.16107329284801
            }
        ]
    },
    {
        "id": "46fc6a80-57ee-4581-ac57-8e520152bf45",
        "name": "Private Edge -Human Parameters Detection ML & Web Dev Challenge",
        "submissionStartDate": "2021-09-08T19:33:52Z",
        "submissionEndDate": "2021-10-02T07:34:48Z",
        "tcoRelevant": false,
        "leaderboard": []
    },
    {
        "id": "c522c9e3-29d3-4788-98db-05748f0842dc",
        "name": "Marathon Match 129",
        "submissionStartDate": "2021-09-07T06:21:47Z",
        "submissionEndDate": "2021-09-22T17:06:36Z",
        "tcoRelevant": true,
        "leaderboard": [
            {
                "name": "ty70",
                "score": 19.46444415427323
            },
            {
                "name": "nika",
                "score": 99.23348750876798
            },
            {
                "name": "highjump",
                "score": 93.16961686321163
            },
            {
                "name": "sogrub",
                "score": 83.4408817259534
            },
            {
                "name": "phocom",
                "score": 91.59223979548476
            },
            {
                "name": "iwashi31",
                "score": 90.21906048184826
            },
            {
                "name": "udon1206",
                "score": 90.98762691773051
            },
            {
                "name": "hari64",
                "score": 57.34827744372827
            },
            {
                "name": "kaede2020",
                "score": 69.47553588654164
            },
            {
                "name": "nailBiter",
                "score": 70.32982704452287
            },
            {
                "name": "ekiden",
                "score": 90.60172626529642
            },
            {
                "name": "NaranbayarU",
                "score": 81.33521748563497
            },
            {
                "name": "yowa",
                "score": 98.19620166686688
            },
            {
                "name": "KKT89",
                "score": 91.39242385145117
            },
            {
                "name": "bowwowforeach",
                "score": 99.24287731121272
            },
            {
                "name": "mooaki",
                "score": 87.90536312098648
            },
            {
                "name": "EvbCFfp1XB",
                "score": 93.15835453599745
            },
            {
                "name": "simanman",
                "score": 98.4656978320184
            },
            {
                "name": "nofto",
                "score": 94.85977090534462
            },
            {
                "name": "ATowerOfHanoi",
                "score": 73.9515982551753
            },
            {
                "name": "KursAndrey",
                "score": 58.897096020213105
            },
            {
                "name": "square1001",
                "score": 96.62544307112108
            },
            {
                "name": "iehn",
                "score": 99.25604521998918
            },
            {
                "name": "mcollier",
                "score": 60.393613426148846
            },
            {
                "name": "shamio",
                "score": 92.30709884547487
            },
            {
                "name": "_Romka_",
                "score": 93.50832919423021
            },
            {
                "name": "vlad_D",
                "score": 89.32383215286261
            },
            {
                "name": "ptoolis",
                "score": 72.82710590887237
            },
            {
                "name": "angwin",
                "score": 84.54075015745683
            },
            {
                "name": "vdave",
                "score": 90.98266430002009
            },
            {
                "name": "my316g",
                "score": 83.74459216075238
            },
            {
                "name": "beginnner101",
                "score": 7.810420433298579
            },
            {
                "name": "siwei88",
                "score": 86.2508670559129
            },
            {
                "name": "cclgc",
                "score": 85.25476555599202
            },
            {
                "name": "houxiang",
                "score": 88.21294275595963
            },
            {
                "name": "wleite",
                "score": 98.61892875590716
            },
            {
                "name": "rmizuta",
                "score": 87.2157907855427
            },
            {
                "name": "mengue",
                "score": 7.810420433298579
            },
            {
                "name": "oreshnik",
                "score": -1
            },
            {
                "name": "sd10000100",
                "score": 80.17959774110807
            },
            {
                "name": "trimo",
                "score": 86.13387143593292
            },
            {
                "name": "hujtomi",
                "score": 79.71895501693172
            },
            {
                "name": "kishore_g84",
                "score": 86.87054309764464
            },
            {
                "name": "Karloid",
                "score": 33.610707420964715
            },
            {
                "name": "tehnar",
                "score": 74.23382660899163
            },
            {
                "name": "goto_isyuku",
                "score": 79.27786637759945
            },
            {
                "name": "okazaki",
                "score": 54.1267113677371
            },
            {
                "name": "tuff",
                "score": 85.13917718735563
            },
            {
                "name": "MvKaio",
                "score": 60.07469682210042
            },
            {
                "name": "tourist",
                "score": 83.20068622107942
            },
            {
                "name": "daisyo",
                "score": 85.6046772433222
            },
            {
                "name": "moshu",
                "score": 82.8392655540462
            },
            {
                "name": "mcw1142",
                "score": 72.85164415270867
            },
            {
                "name": "vgrover21",
                "score": 17.16720768821028
            },
            {
                "name": "boocoo",
                "score": 7.810420433298579
            },
            {
                "name": "IlyaZhukov",
                "score": 38.64818967644166
            },
            {
                "name": "kyo1",
                "score": 77.25324971060563
            }
        ]
    },
    {
        "id": "bec3a1a9-15a1-49d5-83af-ce3f3f5e646f",
        "name": "Reclamation: Streamflow Forecast Rodeo Challenge Series - September",
        "submissionStartDate": "2021-08-24T16:09:57Z",
        "submissionEndDate": "2021-09-30T16:06:41Z",
        "tcoRelevant": false,
        "leaderboard": [
            {
                "name": "TopG",
                "score": -1
            },
            {
                "name": "deven-gqc",
                "score": 27.451153690613417
            },
            {
                "name": "hydrotrek",
                "score": 27.451153690613417
            },
            {
                "name": "fly_fly",
                "score": 43.0170564714079
            },
            {
                "name": "tomy4reel",
                "score": -1
            },
            {
                "name": "number13",
                "score": 38.55941043322704
            },
            {
                "name": "kdpk0197",
                "score": 38.34052195593513
            },
            {
                "name": "LastEmperor",
                "score": 37.97811576240754
            },
            {
                "name": "viyaviya",
                "score": 2.166675848418868
            },
            {
                "name": "tarunjuneja",
                "score": 0.3908145624032362
            },
            {
                "name": "yank01",
                "score": 40.30380060941189
            },
            {
                "name": "J.Bogusz",
                "score": 38.75770645573032
            },
            {
                "name": "salmiaki",
                "score": 49.01346402920782
            },
            {
                "name": "TheRealRoman",
                "score": 42.79026255048762
            },
            {
                "name": "a.lowe",
                "score": -1
            },
            {
                "name": "std",
                "score": 43.92257936808883
            },
            {
                "name": "codingdrone",
                "score": 6.1372684722815976
            },
            {
                "name": "tEarth",
                "score": 40.10220260689388
            },
            {
                "name": "pauli89",
                "score": 6.698447371113872
            },
            {
                "name": "KHGMEC_lstm",
                "score": 22.19737860489525
            },
            {
                "name": "KHGMEC_bc",
                "score": 15.599657912703604
            },
            {
                "name": "KHGMEC_raw",
                "score": 10.711699992988914
            },
            {
                "name": "kukusi",
                "score": 38.3131540219546
            },
            {
                "name": "thothling",
                "score": 33.82908570767968
            },
            {
                "name": "d_a_konovalov",
                "score": 37.792433653546645
            },
            {
                "name": "dsvolkov",
                "score": 43.33706892263632
            },
            {
                "name": "AliGebily",
                "score": 47.42563373682545
            },
            {
                "name": "camaron_ai",
                "score": 30.09017060040057
            },
            {
                "name": "albantor30",
                "score": 42.15640380961086
            },
            {
                "name": "yypark",
                "score": 12.80133835915577
            },
            {
                "name": "tcghanareddy",
                "score": 45.12007126283029
            },
            {
                "name": "yrtchn",
                "score": 37.07439680867377
            },
            {
                "name": "mtmiron",
                "score": 46.80166333623469
            },
            {
                "name": "suresh1187",
                "score": 38.68441361287504
            },
            {
                "name": "rdeggau",
                "score": 0.6418354478836279
            },
            {
                "name": "gardn999",
                "score": 47.046144432358275
            },
            {
                "name": "MarathonTester5",
                "score": 0
            },
            {
                "name": "MarathonTester4",
                "score": 8.547102886524405
            },
            {
                "name": "MarathonTester3",
                "score": 4.41375254737794
            },
            {
                "name": "MarathonTester2",
                "score": 19.202394060291045
            },
            {
                "name": "marathontester1",
                "score": 2.36633008861782
            },
            {
                "name": "now_you_see",
                "score": 25.925862502935086
            },
            {
                "name": "rasyidridha",
                "score": 49.384202906732355
            },
            {
                "name": "rekcahd",
                "score": 49.647128699015674
            },
            {
                "name": "pfr",
                "score": 47.00830785651344
            }
        ]
    },
    {
        "id": "8287c805-1f7e-40c8-9d5d-63a86759f72b",
        "name": "TCO21 Regional Marathon - Lightning Marathon Match 128",
        "submissionStartDate": "2021-08-02T13:38:33Z",
        "submissionEndDate": "2021-08-05T13:45:03Z",
        "tcoRelevant": true,
        "leaderboard": [
            {
                "name": "aropan",
                "score": 31.394571791759677
            },
            {
                "name": "AmAtUrECoDeR",
                "score": 74.01115767162409
            },
            {
                "name": "hari64",
                "score": 50.62240362134496
            },
            {
                "name": "gultai4uk_r",
                "score": 66.5563077789064
            },
            {
                "name": "Inaniwa",
                "score": 80.59357487088359
            },
            {
                "name": "wleite",
                "score": 95.27209715854974
            },
            {
                "name": "MvKaio",
                "score": 63.068150836458976
            },
            {
                "name": "nofto",
                "score": 82.69215440128838
            },
            {
                "name": "Sorting",
                "score": 73.79110319106788
            },
            {
                "name": "jam1729",
                "score": 49.61659879321743
            },
            {
                "name": "beginnner101",
                "score": 22.277707317091362
            },
            {
                "name": "phocom",
                "score": 79.54959538281987
            },
            {
                "name": "bowwowforeach",
                "score": 85.3929018686113
            },
            {
                "name": "titia",
                "score": 46.3122251102784
            },
            {
                "name": "tourist",
                "score": 85.50043429326873
            },
            {
                "name": "EvbCFfp1XB",
                "score": 59.297822739631044
            },
            {
                "name": "my316g",
                "score": 94.0129202109643
            },
            {
                "name": "aryanc403",
                "score": 48.75336150375338
            },
            {
                "name": "Beb7",
                "score": 27.930048200510022
            },
            {
                "name": "q0o0p",
                "score": 48.168381102092894
            },
            {
                "name": "Shubham_Avasthi",
                "score": 49.03110034324848
            },
            {
                "name": "vdave",
                "score": 69.91713531479839
            },
            {
                "name": "jfguo",
                "score": 36.65243812494634
            },
            {
                "name": "ekiden",
                "score": 48.14954069910016
            },
            {
                "name": "iwashi31",
                "score": 87.92491208221705
            },
            {
                "name": "Daiver19",
                "score": 76.95010696807289
            },
            {
                "name": "quimey",
                "score": 63.82747590964144
            },
            {
                "name": "ebicochineal",
                "score": 70.6806261792399
            },
            {
                "name": "dusty.and.rusty",
                "score": 71.59140713138468
            },
            {
                "name": "ATowerOfHanoi",
                "score": 65.8259231905189
            },
            {
                "name": "reg7777",
                "score": 51.58750050266122
            },
            {
                "name": "321blastoff",
                "score": 0.07586164038820276
            },
            {
                "name": "K_lash96",
                "score": -1
            },
            {
                "name": "kaede2020",
                "score": 28.47021173938464
            },
            {
                "name": "mooaki",
                "score": 63.44091078624291
            },
            {
                "name": "ptoolis",
                "score": 34.807083554232754
            },
            {
                "name": "tabr",
                "score": 37.58001692289775
            },
            {
                "name": "al_gol",
                "score": 54.370681695745894
            },
            {
                "name": "AliGebily",
                "score": 24.218669603157934
            },
            {
                "name": "sr.harrison",
                "score": 3.5487193362193366
            },
            {
                "name": "AguaPodrida",
                "score": 49.965662045934366
            },
            {
                "name": "simanman",
                "score": 56.577463061003904
            },
            {
                "name": "a.lowe",
                "score": 7.867135590499594
            },
            {
                "name": "shamio",
                "score": 37.6000210090305
            },
            {
                "name": "toku_",
                "score": 62.18493711077333
            },
            {
                "name": "GoogleHireMe",
                "score": 45.837031299131056
            },
            {
                "name": "MipLetsPlay",
                "score": 48.88042724888549
            },
            {
                "name": "Pena",
                "score": 17.13801357261018
            },
            {
                "name": "Ra16bit",
                "score": 32.38024649769518
            },
            {
                "name": "yowa",
                "score": 76.40947043636581
            },
            {
                "name": "amiune",
                "score": 47.07067241365423
            },
            {
                "name": "frogb",
                "score": 47.4598821614908
            },
            {
                "name": "murrayr",
                "score": 74.70231238626732
            },
            {
                "name": "highjump",
                "score": 56.2585912543861
            },
            {
                "name": "abhiiitcse",
                "score": 32.94075839818484
            },
            {
                "name": "irohitgoyal",
                "score": -1
            },
            {
                "name": "Shruthi2701",
                "score": -1
            },
            {
                "name": "ecto0310",
                "score": 40.17672922289492
            },
            {
                "name": "Kanten-4205",
                "score": 7.230251142867055
            },
            {
                "name": "codecraft15",
                "score": -1
            },
            {
                "name": "palash_04",
                "score": 24.407362865147707
            },
            {
                "name": "vlad_D",
                "score": 47.52522656397458
            },
            {
                "name": "schapke",
                "score": -1
            },
            {
                "name": "yuusanlondon",
                "score": 58.53165719288999
            },
            {
                "name": "rekcahd",
                "score": 54.898415197812916
            },
            {
                "name": "tabae326",
                "score": 42.80658871595536
            },
            {
                "name": "iehn",
                "score": 55.42510403309217
            },
            {
                "name": "yashjain0333",
                "score": 6.938306492534746
            },
            {
                "name": "adr2370",
                "score": 28.486442077874955
            },
            {
                "name": "deathliger",
                "score": 19.512175714704608
            }
        ]
    },
    {
        "id": "2b45beb4-7eee-44ee-8f10-6a91f7e6747f",
        "name": "Reclamation: Streamflow Forecast Rodeo Challenge Series - August",
        "submissionStartDate": "2021-07-24T16:09:07Z",
        "submissionEndDate": "2021-08-31T16:09:00Z",
        "tcoRelevant": false,
        "leaderboard": [
            {
                "name": "AliGebily",
                "score": 36.533077603633274
            },
            {
                "name": "deven-gqc",
                "score": -1
            },
            {
                "name": "number13",
                "score": 34.00266924435174
            },
            {
                "name": "fly_fly",
                "score": 33.94552420766587
            },
            {
                "name": "rasyidridha",
                "score": 45.01304828606559
            },
            {
                "name": "LastEmperor",
                "score": 40.30188691905281
            },
            {
                "name": "bryanyahir03",
                "score": -1
            },
            {
                "name": "yank01",
                "score": 40.11962407905299
            },
            {
                "name": "rekcahd",
                "score": 44.86647443882789
            },
            {
                "name": "andywood",
                "score": -1
            },
            {
                "name": "camaron_ai",
                "score": 16.895763828615152
            },
            {
                "name": "J.Bogusz",
                "score": 36.34223256931387
            },
            {
                "name": "TheRealRoman",
                "score": 38.32180276950562
            },
            {
                "name": "yrtchn",
                "score": 34.041485133100124
            },
            {
                "name": "pauli89",
                "score": 10.643085875388914
            },
            {
                "name": "tEarth",
                "score": 31.85059285833114
            },
            {
                "name": "std",
                "score": 40.49490195117288
            },
            {
                "name": "codingdrone",
                "score": 8.828268176403238
            },
            {
                "name": "kukusi",
                "score": 11.936503027147184
            },
            {
                "name": "KHGMEC_bc",
                "score": 13.38571217594694
            },
            {
                "name": "KHGMEC_lstm",
                "score": 22.424865380215824
            },
            {
                "name": "KHGMEC_raw",
                "score": 12.692334704798144
            },
            {
                "name": "viyaviya",
                "score": 6.772279750744273
            },
            {
                "name": "d_a_konovalov",
                "score": 37.856976461119
            },
            {
                "name": "thothling",
                "score": 32.173772177216854
            },
            {
                "name": "dsvolkov",
                "score": 43.51294970399708
            },
            {
                "name": "a.lowe",
                "score": -1
            },
            {
                "name": "yypark",
                "score": 11.76479801621154
            },
            {
                "name": "MarathonTester5",
                "score": 0
            },
            {
                "name": "MarathonTester4",
                "score": 12.888146015481047
            },
            {
                "name": "MarathonTester3",
                "score": 1.7831808799948972
            },
            {
                "name": "MarathonTester2",
                "score": 22.758149741683777
            },
            {
                "name": "marathontester1",
                "score": 9.051524736730984
            },
            {
                "name": "kdpk0197",
                "score": 35.795083851183456
            },
            {
                "name": "brev",
                "score": 20.575897555801877
            },
            {
                "name": "Kmande",
                "score": 25.31930971645369
            },
            {
                "name": "rdeggau",
                "score": 6.321235118329555
            },
            {
                "name": "albantor30",
                "score": 34.94357954194866
            },
            {
                "name": "salmiaki",
                "score": 35.47613844887375
            },
            {
                "name": "pfr",
                "score": 46.68355156569379
            },
            {
                "name": "mtmiron",
                "score": 45.51040701705843
            },
            {
                "name": "gardn999",
                "score": 41.58596734801221
            },
            {
                "name": "suresh1187",
                "score": 34.1455319239876
            },
            {
                "name": "tcghanareddy",
                "score": 45.43958383912967
            },
            {
                "name": "now_you_see",
                "score": 17.9823915469524
            }
        ]
    }
]